{
  "tyrannosaurus":    { "diet": "Carnivore", "lengthM": 12,  "weightKg": 8000,  "phonetic": "ty-RAN-uh-SOR-us" },
  "velociraptor":     { "diet": "Carnivore", "lengthM": 2,   "weightKg": 15,    "phonetic": "vel-OSS-ih-RAP-tor" },
  "triceratops":      { "diet": "Herbivore", "lengthM": 9,   "weightKg": 8000,  "phonetic": "try-SERR-uh-tops" },
  "stegosaurus":      { "diet": "Herbivore", "lengthM": 9,   "weightKg": 3500,  "phonetic": "STEG-uh-SOR-us" },
  "allosaurus":       { "diet": "Carnivore", "lengthM": 9.5, "weightKg": 2000,  "phonetic": "AL-uh-SOR-us" },
  "brachiosaurus":    { "diet": "Herbivore", "lengthM": 22,  "weightKg": 35000, "phonetic": "BRACK-ee-uh-SOR-us" },
  "diplodocus":       { "diet": "Herbivore", "lengthM": 26,  "weightKg": 12000, "phonetic": "dih-PLOD-uh-kus" },
  "spinosaurus":      { "diet": "Piscivore", "lengthM": 15,  "weightKg": 7400,  "phonetic": "SPINE-uh-SOR-us" },
  "coelophysis":      { "diet": "Carnivore", "lengthM": 3,   "weightKg": 20,    "phonetic": "SEE-lo-FY-sis" },
  "plateosaurus":     { "diet": "Herbivore", "lengthM": 8,   "weightKg": 4000,  "phonetic": "PLAT-ee-uh-SOR-us" },
  "herrerasaurus":    { "diet": "Carnivore", "lengthM": 4,   "weightKg": 210,   "phonetic": "huh-RARE-uh-SOR-us" },
  "iguanodon":        { "diet": "Herbivore", "lengthM": 10,  "weightKg": 3500,  "phonetic": "ig-WA-nuh-don" },
  "ankylosaurus":     { "diet": "Herbivore", "lengthM": 8,   "weightKg": 6000,  "phonetic": "an-KY-luh-SOR-us" },
  "archaeopteryx":    { "diet": "Carnivore", "lengthM": 0.5, "weightKg": 1,     "phonetic": "ar-kee-OP-ter-ix" },
  "carnotaurus":      { "diet": "Carnivore", "lengthM": 8,   "weightKg": 1350,  "phonetic": "KAR-no-TOR-us" },
  "brontosaurus":     { "diet": "Herbivore", "lengthM": 22,  "weightKg": 15000, "phonetic": "BRON-tuh-SOR-us" },
  "apatosaurus":      { "diet": "Herbivore", "lengthM": 23,  "weightKg": 22000, "phonetic": "uh-PAT-uh-SOR-us" },
  "parasaurolophus":  { "diet": "Herbivore", "lengthM": 10,  "weightKg": 2500,  "phonetic": "PA-ruh-saw-ROL-uh-fus" },
  "utahraptor":       { "diet": "Carnivore", "lengthM": 5.5, "weightKg": 300,   "phonetic": "YOO-tah-RAP-tor" },
  "deinonychus":      { "diet": "Carnivore", "lengthM": 3.4, "weightKg": 73,    "phonetic": "dye-NON-ih-kus" },
  "gallimimus":       { "diet": "Omnivore",  "lengthM": 6,   "weightKg": 440,   "phonetic": "GAL-ih-MY-mus" },
  "compsognathus":    { "diet": "Carnivore", "lengthM": 1,   "weightKg": 3,     "phonetic": "komp-sog-NAY-thus" },
  "giganotosaurus":   { "diet": "Carnivore", "lengthM": 13,  "weightKg": 8000,  "phonetic": "JIG-uh-NOTE-uh-SOR-us" },
  "carcharodontosaurus": { "diet": "Carnivore", "lengthM": 12, "weightKg": 7000, "phonetic": "kar-KAR-uh-DON-tuh-SOR-us" },
  "therizinosaurus":  { "diet": "Herbivore", "lengthM": 10,  "weightKg": 5000,  "phonetic": "THAIR-uh-ZEEN-uh-SOR-us" },
  "oviraptor":        { "diet": "Omnivore",  "lengthM": 1.6, "weightKg": 33,    "phonetic": "OH-vih-RAP-tor" },
  "protoceratops":    { "diet": "Herbivore", "lengthM": 2,   "weightKg": 180,   "phonetic": "PROH-toh-SERR-uh-tops" },
  "pachycephalosaurus": { "diet": "Herbivore", "lengthM": 4.5, "weightKg": 450, "phonetic": "PAK-ee-SEF-uh-luh-SOR-us" },
  "dilophosaurus":    { "diet": "Carnivore", "lengthM": 6,   "weightKg": 400,   "phonetic": "dye-LOH-fuh-SOR-us" },
  "ceratosaurus":     { "diet": "Carnivore", "lengthM": 6,   "weightKg": 700,   "phonetic": "seh-RAT-uh-SOR-us" },
  "baryonyx":         { "diet": "Piscivore", "lengthM": 8.5, "weightKg": 1700,  "phonetic": "bah-ree-ON-ix" },
  "maiasaura":        { "diet": "Herbivore", "lengthM": 9,   "weightKg": 3000,  "phonetic": "MY-uh-SOR-uh" },
  "edmontosaurus":    { "diet": "Herbivore", "lengthM": 12,  "weightKg": 4000,  "phonetic": "ed-MON-tuh-SOR-us" },
  "styracosaurus":    { "diet": "Herbivore", "lengthM": 5.5, "weightKg": 2700,  "phonetic": "sty-RAK-uh-SOR-us" },
  "kentrosaurus":     { "diet": "Herbivore", "lengthM": 4.5, "weightKg": 1000,  "phonetic": "KEN-truh-SOR-us" },
  "microraptor":      { "diet": "Carnivore", "lengthM": 0.8, "weightKg": 1,     "phonetic": "MY-kro-RAP-tor" },
  "argentinosaurus":  { "diet": "Herbivore", "lengthM": 35,  "weightKg": 75000, "phonetic": "AR-jen-TEEN-uh-SOR-us" },
  "mamenchisaurus":   { "diet": "Herbivore", "lengthM": 25,  "weightKg": 15000, "phonetic": "mah-MEN-chih-SOR-us" },
  "troodon":          { "diet": "Carnivore", "lengthM": 2.4, "weightKg": 50,    "phonetic": "TROH-uh-don" },
  "megalosaurus":     { "diet": "Carnivore", "lengthM": 6,   "weightKg": 1000,  "phonetic": "MEG-uh-luh-SOR-us" },
  "suchomimus":       { "diet": "Piscivore", "lengthM": 11,  "weightKg": 3800,  "phonetic": "SOOK-uh-MY-mus" },
  "corythosaurus":    { "diet": "Herbivore", "lengthM": 9,   "weightKg": 3000,  "phonetic": "kuh-RITH-uh-SOR-us" },
  "gorgosaurus":      { "diet": "Carnivore", "lengthM": 9,   "weightKg": 2500,  "phonetic": "GOR-guh-SOR-us" },
  "albertosaurus":    { "diet": "Carnivore", "lengthM": 9,   "weightKg": 2000,  "phonetic": "al-BUR-tuh-SOR-us" }
}
